genpurp
